uncrawl/__init__.py
uncrawl/core.py
uncrawl-1.0.2.dist-info/LICENSE
uncrawl-1.0.2.dist-info/METADATA
uncrawl-1.0.2.dist-info/WHEEL
uncrawl-1.0.2.dist-info/top_level.txt
uncrawl-1.0.2.dist-info/RECORD
