Metadata-Version: 2.1
Name: uncrawl
Version: 1.0.2
Summary: A lightweight package for webpage scraping and content extraction.
Home-page: https://github.com/tensaye-o/uncrawl
Author: Tensaye Yuan
Author-email: yyuan.tech@gmail.com
License: Copyright (c) 2023, Tensaye Yuan
License-File: LICENSE
Requires-Dist: newspaper3k
